test_chmod_xiaoxin/__init__.py
test_chmod_xiaoxin/test1.py
test_chmod_xiaoxin/test2.py
test_chmod_xiaoxin/test_chmod_xiaoxin.py
test_chmod_xiaoxin-0.0.6.dist-info/DESCRIPTION.rst
test_chmod_xiaoxin-0.0.6.dist-info/METADATA
test_chmod_xiaoxin-0.0.6.dist-info/RECORD
test_chmod_xiaoxin-0.0.6.dist-info/WHEEL
test_chmod_xiaoxin-0.0.6.dist-info/entry_points.txt
test_chmod_xiaoxin-0.0.6.dist-info/metadata.json
test_chmod_xiaoxin-0.0.6.dist-info/top_level.txt
