Metadata-Version: 2.0
Name: test-chmod-xiaoxin
Version: 0.0.6
Summary: test the right setting of the files
Home-page: https://github.com/xiaoxiaoxin6/test_chmod_xiaoxin.git
Author: xiaoxin
Author-email: xiaoxiaoxin6@163.com
License: UNKNOWN
Platform: UNKNOWN
Classifier: Programming Language :: Python :: 3
Classifier: License :: OSI Approved :: MIT License
Classifier: Operating System :: OS Independent
